runner_info/__init__.py
runner_info/__main__.py
runner_info/runner_info.py
runner_info-0.0.5.dist-info/LICENSE.txt
runner_info-0.0.5.dist-info/WHEEL
runner_info-0.0.5.dist-info/METADATA
runner_info-0.0.5.dist-info/RECORD
